saltyrtc/server/__init__.py
saltyrtc/server/bin.py
saltyrtc/server/common.py
saltyrtc/server/events.py
saltyrtc/server/exception.py
saltyrtc/server/message.py
saltyrtc/server/protocol.py
saltyrtc/server/py.typed
saltyrtc/server/server.py
saltyrtc/server/task.py
saltyrtc/server/typing.py
saltyrtc/server/util.py
saltyrtc.server-5.0.1.dist-info/LICENSE
saltyrtc.server-5.0.1.dist-info/METADATA
saltyrtc.server-5.0.1.dist-info/WHEEL
saltyrtc.server-5.0.1.dist-info/entry_points.txt
saltyrtc.server-5.0.1.dist-info/top_level.txt
saltyrtc.server-5.0.1.dist-info/RECORD
