Metadata-Version: 2.1
Name: saltyrtc.server
Version: 5.0.1
Summary: A SaltyRTC compliant signalling server.
Home-page: https://github.com/saltyrtc/saltyrtc-server-python
Author: Lennart Grahl
Author-email: lennart.grahl@gmail.com
License: MIT
Keywords: saltyrtc signalling signaling websocket websockets nacl
Platform: UNKNOWN
Classifier: Development Status :: 4 - Beta
Classifier: Environment :: Console
Classifier: Environment :: Web Environment
Classifier: Intended Audience :: Developers
Classifier: Intended Audience :: System Administrators
Classifier: License :: OSI Approved :: MIT License
Classifier: Natural Language :: English
Classifier: Operating System :: OS Independent
Classifier: Programming Language :: Python :: 3.6
Classifier: Programming Language :: Python :: 3.7
Classifier: Topic :: Communications
Classifier: Topic :: Internet
Classifier: Topic :: Security
Requires-Dist: libnacl (<2,>=1.5.0)
Requires-Dist: click (>=6.7)
Requires-Dist: websockets (<9,>=8.0)
Requires-Dist: u-msgpack-python (<3,>=2.3)
Provides-Extra: dev
Requires-Dist: pytest (<4,>=3.7.3) ; extra == 'dev'
Requires-Dist: pytest-asyncio (>=0.9.0) ; extra == 'dev'
Requires-Dist: pytest-cov (>=2.5.1) ; extra == 'dev'
Requires-Dist: pytest-mock (>=1.10.0) ; extra == 'dev'
Requires-Dist: flake8 (>=3.7.8) ; extra == 'dev'
Requires-Dist: isort (>=4.3.21) ; extra == 'dev'
Requires-Dist: collective.checkdocs (>=0.2) ; extra == 'dev'
Requires-Dist: Pygments (>=2.2.0) ; extra == 'dev'
Requires-Dist: ordered-set (>=3.0.1) ; extra == 'dev'
Requires-Dist: logbook (<2,>=1.0.0) ; extra == 'dev'
Requires-Dist: mypy (==0.700) ; extra == 'dev'
Provides-Extra: logging
Requires-Dist: logbook (<2,>=1.0.0) ; extra == 'logging'
Provides-Extra: uvloop
Requires-Dist: uvloop (<2,>=0.8.0) ; extra == 'uvloop'
